Metadata-Version: 2.1
Name: gaianet
Version: 0.0.1
Summary: A place holder for a major development
Home-page: https://github.com/ecmwf/gaianet
Author: European Centre for Medium-Range Weather Forecasts (ECMWF)
Author-email: software.support@ecmwf.int
License: Apache License Version 2.0
Keywords: tool
Classifier: Development Status :: 3 - Alpha
Classifier: Intended Audience :: Developers
Classifier: License :: OSI Approved :: Apache Software License
Classifier: Programming Language :: Python :: 3
Classifier: Programming Language :: Python :: 3.10
Classifier: Programming Language :: Python :: Implementation :: CPython
Classifier: Programming Language :: Python :: Implementation :: PyPy
Classifier: Operating System :: OS Independent
License-File: LICENSE
